fifo_async.v
/*
 * Asynchoronus FIFO module with separate read/write clocks, Reset signals.
 *
 * This FIFO module is heavily commented on purpose. Some parts of the code 
 * may look different from common RTL styles, but that decision is  made 
 * intentionally to simplify the design and make it easier to understand — 
 * especially for beginners or for revisiting the logic later.
 *
 * This design uses Gray-coded pointers and double flip-flop synchronizers
 * to safely cross clock domains without metastability.
 *
 * Key features:
 * - Extra MSB in pointers helps differentiate full vs empty conditions.
 * - Full flag is set when write pointer has wrapped and caught up to read pointer.
 * - Empty flag is set when read and write pointers match.
 * - Uses simple register array for storage.
 * 
 */

module fifo_async #(
    parameter depth = 8,
    parameter width = 8
) (
    input [width-1 : 0] data_in,
    input clk_wr, clk_rd, rst_wr, rst_rd,rd, wr,
    output reg [width-1:0] data_out, 
    output full, empty
);
    // Main memory block of the FIFO — it's just a simple register file not the actual module.
    // you can choose to tgive it some other name as well
    // Each entry is 'width' bits wide, and we have 'depth' entries.
    reg [width-1 : 0] fifo [0 : depth-1];

    // This is used for the pointer width just like in synchoronus.
    localparam ptr_depth = $clog2(depth); 

    // We're using one extra bit in the read and write pointers.
    // This helps us distinguish between full and empty states.
    // Without this extra MSB, wr_ptr == rd_ptr would always look like 'empty',
    // but with the extra bit, we can tell when the FIFO has wrapped around. 
    // Binary pointers for write and read positions.
    reg [ptr_depth : 0] wr_ptr_bin,wr_ptr_s1,wr_ptr_s2;
    reg [ptr_depth : 0] rd_ptr_bin,rd_ptr_s1,rd_ptr_s2;

    // Gray-coded pointers derived from binary pointers.
    wire [ptr_depth : 0]wr_ptr_gray,rd_ptr_gray;

    // To keep things clear and avoid confusion while coding, I handled these related parts together:
    // I wrote the binary-to-Gray code conversion for both pointers consecutively,
    // and then the rest of the logic step-by-step.
    // This way, you can easily track both pointers and avoid mistakes,
    // since their operations are complementary to each other.

    // It’s also a personal preference whether you want to do the full and empty condition
    // calculations inside clocked blocks or outside using continuous assignments.
    // I found it more convenient to compute them outside the clock with blocking assignments.

    // Convert binary pointers to Gray code.
    assign wr_ptr_gray = wr_ptr_bin ^ (wr_ptr_bin >> 1);

    assign rd_ptr_gray = rd_ptr_bin ^ (rd_ptr_bin >> 1);

    // Write logic — This logic runs on write clock domain.
    always @(posedge clk_wr or posedge rst_wr) begin
        if (rst_wr) begin
            wr_ptr_bin <= 0;
        end else begin
            if (wr && !full) begin
                fifo[wr_ptr_bin[ptr_depth-1 : 0]] <= data_in;
                wr_ptr_bin <= wr_ptr_bin + 1'b1; // dont forget to increment the pointer
            end 
        end
    end

    // Read logic —This lofic  runs on read clock domain.
    always @(posedge clk_rd or posedge rst_rd) begin
        if (rst_rd) begin
            data_out <= 0;
            rd_ptr_bin <= 0;
        end else begin
            if (rd && !empty) begin
                data_out <= fifo[rd_ptr_bin[ptr_depth-1:0]];
                rd_ptr_bin <= rd_ptr_bin +1'b1; // dont forget to increment the pointer
            end else begin
               if(!rd) begin 
                data_out <= 'bz;
               end 
            end
        end
    end

    //Another important point:
    // The write pointer is synchronized into the read clock domain,
    // and the read pointer is synchronized into the write clock domain.
    // Using Gray code is crucial here because only one bit changes at a time,
    // which helps prevent false full or empty flags due to metastability.
    
    // Synchronize write pointer Gray code into read clock domain.
    // Two flip-flops used to safely cross clock domains.
   always @(posedge clk_rd or posedge rst_rd) begin
        if (rst_rd) begin
            wr_ptr_s1 <= 0;
            wr_ptr_s2 <= 0;
        end else begin
            wr_ptr_s1 <= wr_ptr_gray;
            wr_ptr_s2 <= wr_ptr_s1;
        end
    end
    // Synchronize read pointer Gray code into write clock domain.
    always @(posedge clk_wr or posedge rst_wr) begin
        if (rst_wr) begin
            rd_ptr_s1 <= 0;
            rd_ptr_s2 <= 0;
        end else begin
            rd_ptr_s1 <= rd_ptr_gray;
            rd_ptr_s2 <= rd_ptr_s1;
        end
    end


    // Full flag logic — evaluated in write clock domain.
    // This checks if the write pointer has wrapped around and caught up to the read pointer.
    // We flip the MSB of the write pointer and compare it with the read pointer.

        assign full = {~wr_ptr_gray[ptr_depth], wr_ptr_gray[ptr_depth-1:0]} == rd_ptr_s2;

    // Empty flag logic — evaluated in read clock domain.
    // If the read and write pointers are equal, then the FIFO is empty.

        assign empty = rd_ptr_gray == wr_ptr_s2;


endmodule

fifo_async_tb.v
`timescale 1ns/1ns
`include "fifo_async.v"

module fifo_async_tb;

    parameter WIDTH = 8;

    reg clk_rd, clk_wr, rst_rd, rst_wr;
    reg wr, rd;
    reg [WIDTH-1:0] data_in;
    wire [WIDTH-1:0] data_out;
    wire full, empty;


    fifo_async #( .depth(8), .width(WIDTH) ) uut (
    .data_in(data_in),
    .clk_wr(clk_wr),
    .clk_rd(clk_rd),
    .rst_wr(rst_wr),
    .rst_rd(rst_rd),
    .rd(rd),
    .wr(wr),
    .data_out(data_out),
    .full(full),
    .empty(empty)
    );

    // Clock generation
    initial begin
        clk_wr = 0;
        forever #5 clk_wr = ~clk_wr;  // 10ns write clock
    end

    initial begin
        clk_rd = 0;
        forever #7 clk_rd = ~clk_rd;  // 14ns read clock (asynchronous)
    end

    initial begin
        $dumpfile("fifo_async_tb.vcd");
        $dumpvars(0, fifo_async_tb);
    end

    initial begin
        // Step 1: Initialize all inputs
        rst_wr = 1; rst_rd = 1;
        wr = 0; rd = 0;
        data_in = 8'd0;

        // Step 2: Apply reset for both domains
        #13 rst_wr = 0; rst_rd = 0;

        // Step 3: Write 3 values into the FIFO
        #10 wr = 1; data_in = 8'd10;
        #10        data_in = 8'd20;
        #10        data_in = 8'd30;
        #10 wr = 0;                  // Stop writing

        // Step 4: Read 3 values out of the FIFO
        #10 rd = 1;
        #80 rd = 0;                  // Stop reading

        // Step 5: Fill FIFO to test full condition
        #10 wr = 1; data_in = 8'd40;
        #10        data_in = 8'd50;
        #10        data_in = 8'd60;
        #10        data_in = 8'd70;
        #10        data_in = 8'd80;
        #10        data_in = 8'd90;
        #10        data_in = 8'd100;
        #10        data_in = 8'd120;
        #10 wr = 0;

        // Step 6: Empty the FIFO to test empty condition
        #10 rd = 1;
        #10;
        #10;
        #10;
        #10;
        #10 rd = 0;

        // Done
        #20 $finish;
    end


    initial begin
        $monitor("Time=%0t | rst_wr=%b | rst_rd=%b | wr=%b | rd=%b | data_in=%0d | data_out=%0d | full=%b | empty=%b",
                 $time, rst_wr, rst_rd, wr, rd, data_in, data_out, full, empty);
    end

endmodule

fifo_async_tb.vcd
$date
	Sat Aug 09 05:08:59 2025
$end
$version
	Icarus Verilog
$end
$timescale
	1ns
$end
$scope module fifo_async_tb $end
$var wire 8 ! data_out [7:0] $end
$var wire 1 " empty $end
$var wire 1 # full $end
$var reg 1 $ clk_rd $end
$var reg 1 % clk_wr $end
$var reg 8 & data_in [7:0] $end
$var reg 1 ' rd $end
$var reg 1 ( rst_rd $end
$var reg 1 ) rst_wr $end
$var reg 1 * wr $end
$scope module uut $end
$var wire 1 + clk_rd $end
$var wire 1 , clk_wr $end
$var wire 8 - data_in [7:0] $end
$var wire 1 " empty $end
$var wire 1 # full $end
$var wire 1 . rd $end
$var wire 4 / rd_ptr_gray [3:0] $end
$var wire 1 0 rst_rd $end
$var wire 1 1 rst_wr $end
$var wire 1 2 wr $end
$var wire 4 3 wr_ptr_gray [3:0] $end
$var reg 8 4 data_out [7:0] $end
$var reg 4 5 rd_ptr_bin [3:0] $end
$var reg 4 6 rd_ptr_s1 [3:0] $end
$var reg 4 7 rd_ptr_s2 [3:0] $end
$var reg 4 8 wr_ptr_bin [3:0] $end
$var reg 4 9 wr_ptr_s1 [3:0] $end
$var reg 4 : wr_ptr_s2 [3:0] $end
$upscope $end
$upscope $end
$enddefinitions $end
#0
$dumpvars
b0 :
b0 9
b0 8
b0 7
b0 6
b0 5
b0 4
b0 3
02
11
10
b0 /
0.
b0 -
0,
0+
0*
1)
1(
0'
b0 &
0%
0$
0#
1"
b0 !
$end
#5
1%
1,
#7
1$
1+
#10
0%
0,
#13
0(
00
0)
01
#14
0$
0+
#15
1%
1,
#20
0%
0,
#21
bz 4
bz !
1$
1+
#23
b1010 &
b1010 -
1*
12
#25
b1 3
b1 8
1%
1,
#28
0$
0+
#30
0%
0,
#33
b10100 &
b10100 -
#35
b11 3
b10 8
b1 9
1%
1,
1$
1+
#40
0%
0,
#42
0$
0+
#43
b11110 &
b11110 -
#45
b10 3
b11 8
1%
1,
#49
b1 :
0"
b10 9
1$
1+
#50
0%
0,
#53
0*
02
#55
1%
1,
#56
0$
0+
#60
0%
0,
#63
b1 /
b10 :
b1 5
b1010 4
b1010 !
1$
1+
1'
1.
#65
b1 6
1%
1,
#70
0%
0,
0$
0+
#75
b1 7
1%
1,
#77
b11 /
0"
b10 5
b10100 4
b10100 !
1$
1+
#80
0%
0,
#84
0$
0+
#85
b11 6
1%
1,
#90
0%
0,
#91
b10 /
1"
b11 5
b11110 4
b11110 !
1$
1+
#95
b11 7
b10 6
1%
1,
#98
0$
0+
#100
0%
0,
#105
b10 7
1%
1,
1$
1+
#110
0%
0,
#112
0$
0+
#115
1%
1,
#119
1$
1+
#120
0%
0,
#125
1%
1,
#126
0$
0+
#130
0%
0,
#133
1$
1+
#135
1%
1,
#140
0%
0,
0$
0+
#143
0'
0.
#145
1%
1,
#147
bz 4
bz !
1$
1+
#150
0%
0,
#153
b101000 &
b101000 -
1*
12
#154
0$
0+
#155
b110 3
b100 8
1%
1,
#160
0%
0,
#161
b110 9
1$
1+
#163
b110010 &
b110010 -
#165
b111 3
b101 8
1%
1,
#168
0$
0+
#170
0%
0,
#173
b111100 &
b111100 -
#175
b101 3
b110 8
b110 :
0"
b111 9
1%
1,
1$
1+
#180
0%
0,
#182
0$
0+
#183
b1000110 &
b1000110 -
#185
b100 3
b111 8
1%
1,
#189
b111 :
b100 9
1$
1+
#190
0%
0,
#193
b1010000 &
b1010000 -
#195
b1100 3
b1000 8
1%
1,
#196
0$
0+
#200
0%
0,
#203
b100 :
b1100 9
1$
1+
b1011010 &
b1011010 -
#205
b1101 3
b1001 8
1%
1,
#210
0%
0,
0$
0+
#213
b1100100 &
b1100100 -
#215
b1111 3
b1010 8
1%
1,
#217
b1100 :
b1111 9
1$
1+
#220
0%
0,
#223
b1111000 &
b1111000 -
#224
0$
0+
#225
b1110 3
b1011 8
1%
1,
#230
0%
0,
#231
b1111 :
b1110 9
1$
1+
#233
0*
02
#235
1%
1,
#238
0$
0+
#240
0%
0,
#243
1'
1.
#245
b110 /
b100 5
b101000 4
b101000 !
b1110 :
1%
1,
1$
1+
#250
0%
0,
#252
0$
0+
#255
b110 6
1%
1,
#259
b111 /
b101 5
b110010 4
b110010 !
1$
1+
#260
0%
0,
#265
b110 7
1#
b111 6
1%
1,
#266
0$
0+
#270
0%
0,
#273
b101 /
b110 5
b111100 4
b111100 !
1$
1+
#275
b111 7
0#
b101 6
1%
1,
#280
0%
0,
0$
0+
#285
b101 7
1%
1,
#287
b100 /
b111 5
b1000110 4
b1000110 !
1$
1+
#290
0%
0,
#293
0'
0.
#294
0$
0+
#295
b100 6
1%
1,
#300
0%
0,
#301
bz 4
bz !
1$
1+
#305
b100 7
1%
1,
